behave
flybirds
flybirds_airtest
flybirds_poco
