Metadata-Version: 2.1
Name: wetest-snapcode
Version: 2.0.262
Author: wetest
License: MIT license
Keywords: automation,automated-test,bdd,framework,android,ios,behave
Classifier: Programming Language :: Python :: 3.7
Classifier: Programming Language :: Python :: 3.8
Classifier: Programming Language :: Python :: 3.9
Classifier: Programming Language :: Python :: 3.10
Requires-Python: >=3.7, <3.11
License-File: LICENSE
Requires-Dist: baseImage >=2.1.1
Requires-Dist: click ==8.0.3
Requires-Dist: cos-python-sdk-v5 ~=1.9.25
Requires-Dist: deepdiff >=5.8.1
Requires-Dist: facebook-wda ==1.4.6
Requires-Dist: Flask ~=2.2.5
Requires-Dist: hrpc >=1.0.9
Requires-Dist: jsonpath ==0.82
Requires-Dist: jsonpath-ng >=1.5.3
Requires-Dist: numpy <1.23
Requires-Dist: onnxruntime ==1.14.1
Requires-Dist: opencv-python ~=4.7.0.72
Requires-Dist: paddleocr <=2.6.0
Requires-Dist: paddlepaddle >=2.3.0
Requires-Dist: parse ~=1.19.0
Requires-Dist: parse-type ~=0.6.0
Requires-Dist: Pillow ~=9.5.0
Requires-Dist: protobuf ==3.20.1
Requires-Dist: pyasn1 ==0.4.8
Requires-Dist: pydantic
Requires-Dist: pyOpenSSL <23.2.0,>=22.0.0
Requires-Dist: requests ~=2.28.2
Requires-Dist: rich <13.0.0,>=10.11.0
Requires-Dist: scikit-image ~=0.20.0
Requires-Dist: six
Requires-Dist: tidevice ==0.11.1
Requires-Dist: typer >=0.6.0
Requires-Dist: urllib3 <=1.26.16,>=1.26.10
Requires-Dist: cantools
